reverse_projection/__init__.py
reverse_projection/search/__init__.py
reverse_projection/search/algorithms.py
reverse_projection/search/main.py
reverse_projection/webapis/__init__.py
reverse_projection/webapis/algorithms.py
reverse_projection/webapis/configs.py
reverse_projection/webapis/data.py
reverse_projection/webapis/db.py
reverse_projection/webapis/decomposers.py
reverse_projection/webapis/targets.py
reverse_projection/webapis/utils.py
reverse_projection-0.0.2.5.dist-info/METADATA
reverse_projection-0.0.2.5.dist-info/WHEEL
reverse_projection-0.0.2.5.dist-info/top_level.txt
reverse_projection-0.0.2.5.dist-info/RECORD
